rxn/availability/__init__.py
rxn/availability/availability_combiner.py
rxn/availability/availability_from_database.py
rxn/availability/availability_from_regex.py
rxn/availability/availability_from_smarts.py
rxn/availability/availability_from_smiles.py
rxn/availability/config.py
rxn/availability/databases.py
rxn/availability/defaults.py
rxn/availability/is_available.py
rxn/availability/py.typed
rxn/availability/smiles_availability.py
rxn/availability/utils.py
rxn/availability/resources/__init__.py
rxn/availability/resources/common_compounds.txt
rxn_availability-3.0.0.dist-info/LICENSE
rxn_availability-3.0.0.dist-info/METADATA
rxn_availability-3.0.0.dist-info/WHEEL
rxn_availability-3.0.0.dist-info/top_level.txt
rxn_availability-3.0.0.dist-info/RECORD
