Metadata-Version: 2.1
Name: rxn_availability
Version: 3.0.0
Summary: Describe your project here.
Author: IBM RXN team
Author-email: rxn4chemistry@zurich.ibm.com
Classifier: Operating System :: OS Independent
Classifier: Programming Language :: Python :: 3
Classifier: Programming Language :: Python :: 3.7
Classifier: Programming Language :: Python :: 3.8
Classifier: Programming Language :: Python :: 3.9
Classifier: Programming Language :: Python :: 3.10
Classifier: Programming Language :: Python :: 3.11
Classifier: Programming Language :: Python :: 3.12
License-File: LICENSE
Requires-Dist: importlib-resources >=5.8.0
Requires-Dist: pydantic >=1.9.0
Requires-Dist: pydantic-settings >=2.1.0
Requires-Dist: pymongo >=1.3.1
Requires-Dist: rxn-chem-utils >=1.5.0
Requires-Dist: rxn-utils >=1.1.1
Provides-Extra: dev
Requires-Dist: black >=22.3.0 ; extra == 'dev'
Requires-Dist: flake8 >=3.7.9 ; extra == 'dev'
Requires-Dist: isort >=5.10.1 ; extra == 'dev'
Requires-Dist: mypy >=0.910 ; extra == 'dev'
Requires-Dist: pytest >=5.3.4 ; extra == 'dev'
Requires-Dist: pytest-cov >=2.8.1 ; extra == 'dev'
Requires-Dist: types-setuptools >=57.4.14 ; extra == 'dev'
Provides-Extra: rdkit
Requires-Dist: rdkit >=2021.3.2 ; extra == 'rdkit'
